mecord_crawler/__init__.py
mecord_crawler/aaaapp_crawler.py
mecord_crawler/civitai_crawler.py
mecord_crawler/main.py
mecord_crawler/template_utils.py
mecord_crawler/test.py
mecord_crawler/utils.py
mecord_crawler/bin/__init__.py
mecord_crawler/bin/gellary.txt.py
p_template_crawler-0.1.0.dist-info/LICENSE
p_template_crawler-0.1.0.dist-info/METADATA
p_template_crawler-0.1.0.dist-info/WHEEL
p_template_crawler-0.1.0.dist-info/entry_points.txt
p_template_crawler-0.1.0.dist-info/top_level.txt
p_template_crawler-0.1.0.dist-info/RECORD
