Metadata-Version: 2.1
Name: p-template-crawler
Version: 0.1.0
Summary: template tools
Author: pengjun
Author-email: mr_lonely@foxmail.com
Classifier: Programming Language :: Python :: 3
Classifier: License :: OSI Approved :: MIT License
Classifier: Operating System :: OS Independent
Requires-Python: >=3.7
License-File: LICENSE
Requires-Dist: requests
Requires-Dist: oss2
Requires-Dist: Image
Requires-Dist: Pillow
Requires-Dist: fake-useragent
Requires-Dist: lxml
Requires-Dist: UserAgent
Requires-Dist: urlparser
Requires-Dist: p-template-generator (>=0.1.78)
Requires-Dist: p-template-res (>=0.1.28)
Requires-Dist: yt-dlp (==2023.3.4)
Requires-Dist: requests-toolbelt
Requires-Dist: qrcode
Requires-Dist: googletrans (==4.0.0-rc1)
Requires-Dist: langid
